pylabfea/__init__.py
pylabfea/basic.py
pylabfea/data.py
pylabfea/gui.py
pylabfea/material.py
pylabfea/model.py
pylabfea/training.py
pylabfea-4.4.1.dist-info/licenses/LICENSE
pylabfea-4.4.1.dist-info/METADATA
pylabfea-4.4.1.dist-info/WHEEL
pylabfea-4.4.1.dist-info/top_level.txt
pylabfea-4.4.1.dist-info/RECORD
