Metadata-Version: 2.4
Name: pylabfea
Version: 4.4.1
Summary: Python Laboratory for Finite Element Analysis
Author: Ronak Shoghi, Jan Schmidt
Author-email: Alexander Hartmaier <alexander.hartmaier@rub.de>
License-Expression: GPL-3.0-only
Classifier: Development Status :: 4 - Beta
Classifier: Intended Audience :: Science/Research
Classifier: Natural Language :: English
Classifier: Programming Language :: Python :: 3.12
Classifier: Programming Language :: Python :: 3.13
Requires-Python: >=3
License-File: LICENSE
Requires-Dist: numpy
Requires-Dist: matplotlib
Requires-Dist: scipy
Requires-Dist: scikit-learn
Requires-Dist: pytest
Provides-Extra: test
Requires-Dist: pytest>=3; extra == "test"
Provides-Extra: dev
Requires-Dist: pytest-runner; extra == "dev"
Requires-Dist: black; extra == "dev"
Requires-Dist: build; extra == "dev"
Requires-Dist: twine; extra == "dev"
Dynamic: license-file
